topsis_banaj_101916008
