Metadata-Version: 2.1
Name: topsis-banaj-101916008
Version: 1.1.1
Summary: It's a package that calcuates Topsis score and ranks accordingly
Home-page: https://github.com/banajbedi/topsis_banaj_101916008
Download-URL: https://github.com/banajbedi/topsis_banaj_101916008/archive/refs/tags/v1.1.1.tar.gz
Author: Banaj Bedi
Author-email: banaj7@gmail.com
License: MIT
Platform: UNKNOWN
Classifier: Programming Language :: Python :: 3
Classifier: License :: OSI Approved :: MIT License
Classifier: Operating System :: OS Independent
License-File: LICENSE
